cleverswarm/__init__.py
cleverswarm-0.1.0.dist-info/licenses/LICENSE
cleverswarm-0.1.0.dist-info/METADATA
cleverswarm-0.1.0.dist-info/WHEEL
cleverswarm-0.1.0.dist-info/entry_points.txt
cleverswarm-0.1.0.dist-info/top_level.txt
cleverswarm-0.1.0.dist-info/RECORD
