Metadata-Version: 2.4
Name: cleverswarm
Version: 0.1.0
Summary: CleverSwarm Python Client for interacting with CleverSwarm API
Author-email: CleverThis <contact@cleverthis.com>
License: Apache-2.0
Project-URL: Homepage, https://github.com/cleverthis/cleverswarm-python-client
Project-URL: Bug Tracker, https://github.com/cleverthis/cleverswarm-python-client/issues
Classifier: Programming Language :: Python :: 3
Classifier: License :: OSI Approved :: Apache Software License
Classifier: Operating System :: OS Independent
Classifier: Intended Audience :: Developers
Classifier: Intended Audience :: Science/Research
Classifier: Topic :: Scientific/Engineering :: Artificial Intelligence
Classifier: Topic :: Software Development :: Libraries :: Python Modules
Requires-Python: >=3.8
License-File: LICENSE
Requires-Dist: requests>=2.28.0
Provides-Extra: dev
Requires-Dist: pytest>=7.0.0; extra == "dev"
Requires-Dist: pytest-cov>=4.0.0; extra == "dev"
Requires-Dist: black>=23.0.0; extra == "dev"
Requires-Dist: isort>=5.10.0; extra == "dev"
Requires-Dist: flake8>=6.0.0; extra == "dev"
Dynamic: license-file
